pymsyt-0.3.2.dist-info/METADATA
pymsyt-0.3.2.dist-info/WHEEL
pymsyt.cpython-37m-x86_64-linux-gnu.so
pymsyt-0.3.2.dist-info/RECORD
