Metadata-Version: 2.1
Name: pymsyt
Version: 0.3.2
Classifier: Programming Language :: Rust
Classifier: Operating System :: OS Independent
Classifier: Development Status :: 4 - Beta
Summary: MSBT editing in Python using MSYT
Home-Page: https://github.com/NiceneNerd/PyMsyt/
Author: Caleb Smith <macadamiadaze@gmail.com>
Author-Email: Caleb Smith <macadamiadaze@gmail.com>
License: MIT
